LICENSE
README.md
setup.cfg
setup.py
FunPayNexusAPI/__init__.py
FunPayNexusAPI.egg-info/PKG-INFO
FunPayNexusAPI.egg-info/SOURCES.txt
FunPayNexusAPI.egg-info/dependency_links.txt
FunPayNexusAPI.egg-info/requires.txt
FunPayNexusAPI.egg-info/top_level.txt
FunPayNexusAPI/account/__init__.py
FunPayNexusAPI/account/client.py
FunPayNexusAPI/exceptions/__init__.py
FunPayNexusAPI/exceptions/errors.py
FunPayNexusAPI/types/__init__.py
FunPayNexusAPI/types/methods.py
FunPayNexusAPI/types/utils.py