Metadata-Version: 2.1
Name: FunPayNexusAPI
Version: 0.0.4
Summary: This is a convenient tool for developing and working with the site funpay.com
Home-page: https://github.com/Sema4ka0/FunPay-API
Author: Sema4ka0
Author-email: seem.git@gmail.com
Project-URL: GitHub, https://github.com/Sema4ka0/FunPay-API
Project-URL: Chanel, https://t.me/FunPayNexus
Keywords: funpay api FunPayAPI tool bot tg lib
Classifier: Programming Language :: Python
Classifier: Programming Language :: Python :: 3.8
Classifier: Programming Language :: Python :: 3.9
Classifier: Programming Language :: Python :: 3.10
Classifier: Programming Language :: Python :: 3.11
Classifier: Programming Language :: Python :: 3.12
Classifier: License :: OSI Approved :: MIT License
Classifier: Operating System :: OS Independent
Requires-Python: >=3.8
License-File: LICENSE
